maskpostgresdata/__init__.py
maskpostgresdata/management/__init__.py
maskpostgresdata/management/commands/__init__.py
maskpostgresdata/management/commands/dump_masked_data.py
django_maskpostgresdata-0.2.1.dist-info/METADATA
django_maskpostgresdata-0.2.1.dist-info/WHEEL
django_maskpostgresdata-0.2.1.dist-info/top_level.txt
django_maskpostgresdata-0.2.1.dist-info/RECORD
