Metadata-Version: 2.1
Name: django-maskpostgresdata
Version: 0.2.1
Summary: Creates a pg_dumpish output which masks data without saving changes to the source database.
Home-page: https://github.com/developersociety/django-maskpostgresdata
Author: Developer Society
Author-email: hello@dev.ngo
License: BSD
Requires-Dist: django (>=4.2)
Requires-Dist: psycopg (>=3.1.8)
